fastapi_to_openapi/__init__.py
fastapi_to_openapi/main.py
fastapi_to_openapi-0.2.2.dist-info/LICENSE
fastapi_to_openapi-0.2.2.dist-info/METADATA
fastapi_to_openapi-0.2.2.dist-info/WHEEL
fastapi_to_openapi-0.2.2.dist-info/entry_points.txt
fastapi_to_openapi-0.2.2.dist-info/RECORD
